tree_it/__init__.py
tree_it/cli.py
treeit_cli-1.0.0.dist-info/licenses/LICENSE
treeit_cli-1.0.0.dist-info/METADATA
treeit_cli-1.0.0.dist-info/WHEEL
treeit_cli-1.0.0.dist-info/entry_points.txt
treeit_cli-1.0.0.dist-info/top_level.txt
treeit_cli-1.0.0.dist-info/RECORD
