Metadata-Version: 2.4
Name: treeit-cli
Version: 1.0.0
Summary: CLI tool to generate a directory tree view of your project
Author: Damien Bureau
License: MIT
License-File: LICENSE
Dynamic: license-file
